src/__init__.py
src/main.py
tests/__init__.py
tests/test_add.py
vicferbal_pycicd-1.0.4.dist-info/METADATA
vicferbal_pycicd-1.0.4.dist-info/WHEEL
vicferbal_pycicd-1.0.4.dist-info/top_level.txt
vicferbal_pycicd-1.0.4.dist-info/RECORD
