Metadata-Version: 2.4
Name: vicferbal_pycicd
Version: 1.0.4
Summary: Descripción 
Author: Víctor Manuel Ferrández Ballester
Author-email: vicferbal@alu.edu.gva.es
Requires-Dist: pytest
Requires-Dist: flake8
Dynamic: author
Dynamic: author-email
Dynamic: requires-dist
Dynamic: summary
